clypher/__init__.py
clypher/__main__.py
clypher/_console.py
clypher/_version.py
clypher/cli/__init__.py
clypher/cli/main.py
clypher/cli/managers.py
clypher/cli/messages.py
clypher/cli/commands/__init__.py
clypher/cli/commands/decryption.py
clypher/cli/commands/encryption.py
clypher/cli/commands/version.py
clypher/encryptors/__init__.py
clypher/encryptors/base_encryptor.py
clypher/encryptors/fernet_encryptor.py
clypher/engines/__init__.py
clypher/engines/base_engine.py
clypher/engines/fernet_engine.py
clypher/file_handlers/__init__.py
clypher/file_handlers/base_filehandler.py
clypher/file_handlers/file_handler.py
clypher/import_handler/__init__.py
clypher/import_handler/import_handler.py
clypher/logging_config/__init__.py
clypher/logging_config/logger_config.py
clypher-0.4.dist-info/METADATA
clypher-0.4.dist-info/WHEEL
clypher-0.4.dist-info/licenses/LICENSE
clypher-0.4.dist-info/RECORD
