Metadata-Version: 2.3
Name: Clypher
Version: 0.4
Summary: Encrypt and decrypt from the command line.
Project-URL: Homepage, https://github.com/maxacan/clypher
Project-URL: Issues, https://github.com/maxacan/clypher/issues
Project-URL: Documentation, https://maxacan.github.io/clypher
Author-email: Maximiliano Cancelarich <maximilianoacan@gmail.com>
License-File: LICENSE
Classifier: Development Status :: 3 - Alpha
Classifier: License :: OSI Approved :: GNU General Public License v3 (GPLv3)
Classifier: Operating System :: OS Independent
Classifier: Programming Language :: Python :: 3
Requires-Python: >=3.10
Requires-Dist: cryptography
Requires-Dist: typer[all]
